crow_econometrics/__init__.py
crow_econometrics/crow_econometrics.py
crow_econometrics/models.py
crow_econometrics-0.1.0.dist-info/LICENSE
crow_econometrics-0.1.0.dist-info/METADATA
crow_econometrics-0.1.0.dist-info/WHEEL
crow_econometrics-0.1.0.dist-info/RECORD
