Metadata-Version: 2.3
Name: crow_econometrics
Version: 0.1.0
Summary: Econometrics for All!
License: MIT
Author: ir. R. Jaspers
Requires-Python: >=3.12,<4.0
Classifier: License :: OSI Approved :: MIT License
Classifier: Programming Language :: Python :: 3
Classifier: Programming Language :: Python :: 3.12
Classifier: Programming Language :: Python :: 3.13
Requires-Dist: numpy (>=2.3.1,<3.0.0)
Requires-Dist: pandas (>=2.3.0,<3.0.0)
